{
  "type": "FeatureCollection",
  "features": [
    {
      "type": "Feature",
      "properties": {
        "medallion": "86485F0B1CBDDD6FB6C993011A28B15D",
        "passengers": "1",
        "fare": "5",
        "paymenttype": "CSH",
        "surcharge": "0.5",
        "mtatax": "0.5",
        "tip": "0",
        "tolls": "0",
        "total": "6",
        "pickuptime": "2/6/13 6:00",
        "dropofftime": "2/6/13 6:03",
        "nextpickuptime": "2/6/13 6:11",
        "key": "0",
        "hasfare": true
      },
      "geometry": {
        "type": "LineString",
        "coordinates": [
          [
            -73.97023,
            40.79424
          ],
          [
            -73.96987,
            40.79474
          ],
          [
            -73.96942,
            40.79536
          ],
          [
            -73.96896,
            40.79599
          ],
          [
            -73.96849,
            40.79662
          ],
          [
            -73.96804,
            40.79725
          ],
          [
            -73.96758,
            40.79787
          ],
          [
            -73.96712,
            40.7985
          ],
          [
            -73.96665,
            40.79914
          ],
          [
            -73.9662,
            40.79978
          ],
          [
            -73.96572,
            40.80043
          ],
          [
            -73.96572,
            40.80043
          ],
          [
            -73.96633,
            40.8007
          ],
          [
            -73.96721,
            40.80107
          ],
          [
            -73.96777,
            40.80131
          ],
          [
            -73.96777,
            40.80131
          ],
          [
            -73.96769,
            40.80217
          ],
          [
            -73.96769,
            40.80229
          ],
          [
            -73.96767,
            40.80241
          ],
          [
            -73.96764,
            40.80253
          ],
          [
            -73.96762,
            40.80262
          ],
          [
            -73.96757,
            40.80275
          ],
          [
            -73.9675,
            40.80291
          ],
          [
            -73.96746,
            40.80299
          ],
          [
            -73.96742,
            40.80307
          ],
          [
            -73.96708,
            40.80354
          ],
          [
            -73.96661,
            40.80414
          ],
          [
            -73.96614,
            40.8048
          ],
          [
            -73.96595,
            40.80505
          ],
          [
            -73.96568,
            40.80542
          ],
          [
            -73.96522,
            40.80605
          ],
          [
            -73.96476,
            40.80667
          ],
          [
            -73.9644,
            40.80717
          ]
        ]
      }
    },
    {
      "type": "Feature",
      "properties": {
        "medallion": "86485F0B1CBDDD6FB6C993011A28B15D",
        "passengers": "1",
        "fare": "7.5",
        "paymenttype": "CSH",
        "surcharge": "0",
        "mtatax": "0.5",
        "tip": "0",
        "tolls": "0",
        "total": "8",
        "pickuptime": "2/6/13 6:00",
        "dropofftime": "2/6/13 6:28",
        "nextpickuptime": "2/6/13 6:40",
        "key": "1",
        "hasfare": true
      },
      "geometry": {
        "type": "LineString",
        "coordinates": [
          [
            -73.96653,
            40.80459
          ],
          [
            -73.9668,
            40.80422
          ],
          [
            -73.96724,
            40.80362
          ],
          [
            -73.96763,
            40.80308
          ],
          [
            -73.96768,
            40.80298
          ],
          [
            -73.96772,
            40.80288
          ],
          [
            -73.9678,
            40.80268
          ],
          [
            -73.96784,
            40.80253
          ],
          [
            -73.96787,
            40.80241
          ],
          [
            -73.9679,
            40.80225
          ],
          [
            -73.96801,
            40.80142
          ],
          [
            -73.96808,
            40.80057
          ],
          [
            -73.96811,
            40.80043
          ],
          [
            -73.96812,
            40.80036
          ],
          [
            -73.96815,
            40.80026
          ],
          [
            -73.96818,
            40.80017
          ],
          [
            -73.96823,
            40.80003
          ],
          [
            -73.9683,
            40.79983
          ],
          [
            -73.96864,
            40.79915
          ],
          [
            -73.96908,
            40.79851
          ],
          [
            -73.96954,
            40.79787
          ],
          [
            -73.97,
            40.79725
          ],
          [
            -73.97046,
            40.79664
          ],
          [
            -73.97093,
            40.79601
          ],
          [
            -73.9714,
            40.7954
          ],
          [
            -73.97165,
            40.79504
          ],
          [
            -73.97189,
            40.79471
          ],
          [
            -73.97207,
            40.79449
          ],
          [
            -73.97224,
            40.79427
          ],
          [
            -73.97241,
            40.79405
          ],
          [
            -73.97253,
            40.79387
          ],
          [
            -73.97284,
            40.7934
          ],
          [
            -73.97333,
            40.79277
          ],
          [
            -73.97377,
            40.79214
          ],
          [
            -73.97424,
            40.79152
          ],
          [
            -73.97471,
            40.79088
          ],
          [
            -73.97515,
            40.79026
          ],
          [
            -73.97561,
            40.78965
          ],
          [
            -73.97607,
            40.78902
          ],
          [
            -73.97663,
            40.78837
          ],
          [
            -73.97719,
            40.78771
          ],
          [
            -73.97773,
            40.78709
          ],
          [
            -73.97818,
            40.78647
          ],
          [
            -73.97868,
            40.78582
          ],
          [
            -73.97868,
            40.78582
          ],
          [
            -73.97848,
            40.78574
          ],
          [
            -73.97781,
            40.78547
          ]
        ]
      }
    },
     {
      "type": "Feature",
      "properties": {
        "medallion": "86485F0B1CBDDD6FB6C993011A28B15D",
        "passengers": "1",
        "fare": "7.5",
        "paymenttype": "CSH",
        "surcharge": "0",
        "mtatax": "0.5",
        "tip": "0",
        "tolls": "0",
        "total": "8",
        "pickuptime": "2/6/13 6:11",
        "dropofftime": "2/6/13 6:19",
        "nextpickuptime": "2/6/13 6:21",
        "key": "2",
        "hasfare": true
      },
      "geometry": {
        "type": "LineString",
        "coordinates": [
          [
            -73.96692,
            40.79372
          ],
          [
            -73.96704,
            40.79356
          ],
          [
            -73.96704,
            40.79356
          ],
          [
            -73.96987,
            40.79474
          ],
          [
            -73.97121,
            40.7953
          ],
          [
            -73.9714,
            40.7954
          ],
          [
            -73.97273,
            40.79593
          ],
          [
            -73.97412,
            40.79653
          ],
          [
            -73.9743,
            40.7966
          ],
          [
            -73.9743,
            40.7966
          ],
          [
            -73.9742,
            40.79674
          ],
          [
            -73.97418,
            40.79678
          ],
          [
            -73.97416,
            40.79682
          ],
          [
            -73.97415,
            40.79684
          ],
          [
            -73.97414,
            40.79687
          ],
          [
            -73.97413,
            40.7969
          ],
          [
            -73.97412,
            40.79692
          ],
          [
            -73.97412,
            40.79695
          ],
          [
            -73.97411,
            40.79699
          ],
          [
            -73.97411,
            40.79703
          ],
          [
            -73.97411,
            40.79708
          ],
          [
            -73.97412,
            40.79713
          ],
          [
            -73.97414,
            40.79729
          ],
          [
            -73.97416,
            40.79746
          ],
          [
            -73.97417,
            40.79755
          ],
          [
            -73.97417,
            40.79764
          ],
          [
            -73.97416,
            40.79771
          ],
          [
            -73.97416,
            40.79776
          ],
          [
            -73.97414,
            40.79784
          ],
          [
            -73.97413,
            40.79792
          ],
          [
            -73.97409,
            40.79802
          ],
          [
            -73.97406,
            40.79811
          ],
          [
            -73.97402,
            40.79818
          ],
          [
            -73.97398,
            40.79827
          ],
          [
            -73.97394,
            40.79834
          ],
          [
            -73.9739,
            40.79841
          ],
          [
            -73.97384,
            40.79849
          ],
          [
            -73.97378,
            40.79858
          ],
          [
            -73.97374,
            40.79863
          ],
          [
            -73.97368,
            40.79871
          ],
          [
            -73.97362,
            40.79878
          ],
          [
            -73.97344,
            40.799
          ],
          [
            -73.97329,
            40.79919
          ],
          [
            -73.97297,
            40.79955
          ],
          [
            -73.97283,
            40.79969
          ],
          [
            -73.97274,
            40.79978
          ],
          [
            -73.97263,
            40.79989
          ],
          [
            -73.97255,
            40.79995
          ],
          [
            -73.97245,
            40.80004
          ],
          [
            -73.97236,
            40.80011
          ],
          [
            -73.97228,
            40.80017
          ],
          [
            -73.97217,
            40.80024
          ],
          [
            -73.97204,
            40.80033
          ],
          [
            -73.97192,
            40.80041
          ],
          [
            -73.97176,
            40.80052
          ],
          [
            -73.97166,
            40.80054
          ],
          [
            -73.97159,
            40.80057
          ],
          [
            -73.97145,
            40.80068
          ],
          [
            -73.9714,
            40.80075
          ],
          [
            -73.97129,
            40.80089
          ],
          [
            -73.9712,
            40.80104
          ],
          [
            -73.97025,
            40.80235
          ],
          [
            -73.96951,
            40.80335
          ],
          [
            -73.96931,
            40.80364
          ],
          [
            -73.96907,
            40.804
          ],
          [
            -73.96886,
            40.8043
          ],
          [
            -73.96854,
            40.80483
          ],
          [
            -73.96826,
            40.80536
          ],
          [
            -73.96807,
            40.80572
          ],
          [
            -73.96796,
            40.80595
          ],
          [
            -73.9674,
            40.80695
          ],
          [
            -73.96703,
            40.8075
          ],
          [
            -73.96698,
            40.80759
          ],
          [
            -73.96698,
            40.80759
          ],
          [
            -73.96684,
            40.80754
          ],
          [
            -73.96632,
            40.80732
          ]
        ]
      }
    },
    {
      "type": "Feature",
      "properties": {
        "pickuptime": "2/6/13 6:19",
        "dropofftime": "2/6/13 6:21",
        "key": "3",
        "hasfare": true
      },
      "geometry": {
        "type": "LineString",
        "coordinates": [
          [
            -73.96632,
            40.80732
          ],
          [
            -73.96618,
            40.80726
          ],
          [
            -73.96496,
            40.80675
          ],
          [
            -73.96496,
            40.80675
          ],
          [
            -73.9654,
            40.80612
          ],
          [
            -73.96587,
            40.8055
          ],
          [
            -73.96618,
            40.80509
          ],
          [
            -73.96633,
            40.80487
          ],
          [
            -73.96653,
            40.80459
          ]
        ]
      }
    }    
  ]
}